libhreels/Auger.py
libhreels/HREELS.py
libhreels/LEED.py
libhreels/NoExpLogbook.py
libhreels/README.md
libhreels/ViewAuger.py
libhreels/ViewHREELS.py
libhreels/__init__.py
libhreels/calcHREELS20.png
libhreels/calcHREELS20.py
libhreels/dielectrics20.py
libhreels/expLogbook.py
libhreels/materials20.json
libhreels/mod_doeels.mod
libhreels/myBoson.cpython-310-x86_64-linux-gnu.so
libhreels/myBoson.cpython-312-x86_64-linux-gnu.so
libhreels/myBoson.cpython-36m-x86_64-linux-gnu.so
libhreels/myBoson.cpython-38-x86_64-linux-gnu.so
libhreels/myBoson.f90
libhreels/myBoson.o
libhreels/myEels20.cpython-310-x86_64-linux-gnu.so
libhreels/myEels20.cpython-312-x86_64-linux-gnu.so
libhreels/myEels20.cpython-38-x86_64-linux-gnu.so
libhreels/myEels20.f90
libhreels/viewauger.ui
libhreels/viewhreels.ui
libhreels/viewhreels_dialog.ui
libhreels-2.3.1.dist-info/METADATA
libhreels-2.3.1.dist-info/WHEEL
libhreels-2.3.1.dist-info/entry_points.txt
libhreels-2.3.1.dist-info/RECORD
