Metadata-Version: 2.3
Name: libhreels
Version: 2.3.1
Summary: Handling, simulating, and plotting HREELS and Auger spectroscopy data
Author: Wolf Widdra
Author-email: wolf.widdra@physik.uni-halle.de
Classifier: Programming Language :: Python :: 2
Classifier: Programming Language :: Python :: 2.7
Classifier: Programming Language :: Python :: 3
Classifier: Programming Language :: Python :: 3.4
Classifier: Programming Language :: Python :: 3.5
Classifier: Programming Language :: Python :: 3.6
Classifier: Programming Language :: Python :: 3.7
Classifier: Programming Language :: Python :: 3.8
Classifier: Programming Language :: Python :: 3.9
Classifier: Programming Language :: Python :: 3.10
Classifier: Programming Language :: Python :: 3.11
Classifier: Programming Language :: Python :: 3.12
Classifier: Programming Language :: Python :: 3.13
Project-URL: Homepage, https://gitlab.informatik.uni-halle.de/e3fm8/libhreels
